throttle_openai/__init__.py
throttle_openai/chat.py
throttle_openai/rate_limiter.py
throttle_openai/tokens.py
throttle_openai/utils.py
throttle_openai-0.2.0.dist-info/LICENSE
throttle_openai-0.2.0.dist-info/METADATA
throttle_openai-0.2.0.dist-info/WHEEL
throttle_openai-0.2.0.dist-info/RECORD
