Metadata-Version: 2.1
Name: throttle-openai
Version: 0.2.0
Summary: Concurrent Fast OpenAI calls with Automatic Rate Limiting to avoid hitting limits. Structured Outputs with Pydantic Base Models.
License: MIT
Author: Goutham
Author-email: goutham794@gmail.com
Requires-Python: >=3.9
Classifier: License :: OSI Approved :: MIT License
Classifier: Programming Language :: Python :: 3
Classifier: Programming Language :: Python :: 3.9
Classifier: Programming Language :: Python :: 3.10
Classifier: Programming Language :: Python :: 3.11
Classifier: Programming Language :: Python :: 3.12
Classifier: Programming Language :: Python :: 3.13
Requires-Dist: aiohttp (>=3.11.9,<4.0.0)
Requires-Dist: loguru (>=0.7.2,<0.8.0)
Requires-Dist: pydantic (>=2.10.3,<3.0.0)
Requires-Dist: tiktoken (>=0.8.0,<0.9.0)
